django_admin_workflow/__init__.py
django_admin_workflow/admin.py
django_admin_workflow/apps.py
django_admin_workflow/models.py
django_admin_workflow/tests.py
django_admin_workflow/utils.py
django_admin_workflow/views.py
django_admin_workflow/locale/fr/LC_MESSAGES/django.mo
django_admin_workflow/locale/fr/LC_MESSAGES/django.po
django_admin_workflow/management/commands/_private.py
django_admin_workflow/management/commands/add_sample.py
django_admin_workflow/management/commands/gen_workflow_template.py
django_admin_workflow/management/commands/import_workflow.py
django_admin_workflow/management/commands/run_executors.py
django_admin_workflow/migrations/0001_initial.py
django_admin_workflow/migrations/__init__.py
django_admin_workflow/templates/admin/app_index.html
django_admin_workflow/templates/admin/app_list.html
django_admin_workflow/templates/admin/change_list.html
django_admin_workflow/templates/admin/index.html
django_admin_workflow/templates/admin/django_admin_workflow/app_index.html
django_admin_workflow/templates/admin/django_admin_workflow/rolepermission/change_form.html
django_admin_workflow/templates/django_admin_workflow/change_form.html
django_admin_workflow/templates/django_admin_workflow/graph.html
django_admin_workflow/templates/django_admin_workflow/submit_line.html
django_admin_workflow/templates/django_admin_workflow/toml.html
django_admin_workflow/templates/django_admin_workflow/edit_inline/tabular.html
django_admin_workflow/templates/django_admin_workflow/mail/notif.txt
django_admin_workflow/test/__init__.py
django_admin_workflow/test/base.py
django_admin_workflow/test/helpers.py
django_admin_workflow-0.8.2.dist-info/LICENSE
django_admin_workflow-0.8.2.dist-info/METADATA
django_admin_workflow-0.8.2.dist-info/WHEEL
django_admin_workflow-0.8.2.dist-info/top_level.txt
django_admin_workflow-0.8.2.dist-info/RECORD
