Metadata-Version: 2.1
Name: django_admin_workflow
Version: 0.8.2
Summary: A workflow app for django admin
Home-page: https://github.com/esimorre/django-admin-workflow
Project-URL: Bug Reports, https://github.com/esimorre/django-admin-workflow/issues
Project-URL: Source, https://github.com/esimorre/django-admin-workflow
Keywords: django,workflow
Platform: any
Classifier: Development Status :: 4 - Beta
Classifier: Intended Audience :: Developers
Classifier: Topic :: Software Development :: Libraries :: Python Modules
Classifier: Framework :: Django
Classifier: License :: OSI Approved :: BSD License
Classifier: Programming Language :: Python :: 3
Classifier: Programming Language :: Python :: 3.7
Classifier: Programming Language :: Python :: 3.8
Classifier: Programming Language :: Python :: 3.9
Classifier: Programming Language :: Python :: 3.10
Classifier: Programming Language :: Python :: 3.11
Classifier: Programming Language :: Python :: 3.12
Classifier: Programming Language :: Python :: 3 :: Only
License-File: LICENSE
Requires-Dist: django
Requires-Dist: tomli
